cityiq/__init__.py
cityiq/api.py
cityiq/asset.py
cityiq/clean_events.py
cityiq/config.py
cityiq/exceptions.py
cityiq/location.py
cityiq/task.py
cityiq/token.py
cityiq/util.py
cityiq/cli/__init__.py
cityiq/cli/config.py
cityiq/cli/default-config.yaml
cityiq/cli/events.py
cityiq/cli/nodes.py
cityiq/cli/util.py
cityiq-0.1.5.dist-info/AUTHORS.rst
cityiq-0.1.5.dist-info/LICENSE.txt
cityiq-0.1.5.dist-info/METADATA
cityiq-0.1.5.dist-info/WHEEL
cityiq-0.1.5.dist-info/entry_points.txt
cityiq-0.1.5.dist-info/top_level.txt
cityiq-0.1.5.dist-info/RECORD
