Metadata-Version: 2.1
Name: cityiq
Version: 0.1.5
Summary: Python access to the CityIQ api.
Home-page: https://github.com/sandiegodata/cityiq
Author: Eric Busboom
Author-email: eric@civicknowledge.com
License: mit
Platform: any
Classifier: Development Status :: 4 - Beta
Classifier: Programming Language :: Python
Requires-Python: >=3.4
Requires-Dist: slugify
Requires-Dist: requests
Requires-Dist: websocket-client
Requires-Dist: pytz
Requires-Dist: pyyaml
Requires-Dist: python-dateutil
Provides-Extra: testing
Requires-Dist: pytest ; extra == 'testing'
Requires-Dist: pytest-cov ; extra == 'testing'
